{"county": "Dallas", "executionId": "468", "race": "Black", "link": "http://www.tdcj.state.tx.us/stat/dr_info/bradfordgaylandlast.html", "prisonerId": "966", "firstName": "Gayland", "date": "1/6/2011", "lastName": "Bradford", "age": "42", "statement": "Noel, I love you man. You have been there for me through thick and thin, you and Brigitta. Be there for each other. I am at peace, we have no worries, just as I have no more worries. To the victim's family, may you be at peace also. Noel, I love you man. You have been there for me through thick and thin, you and Brigitta. Be there for each other. I am at peace, we have no worries, just as I have no more worries. To the victim's family, may you be at peace also."}